{
  "2330": {
    "price": 2415.0,
    "change": -50.0,
    "changePct": -2.03,
    "weekChangePct": -2.03,
    "volume": 34681,
    "pe": null,
    "institutionalScore": 50,
    "institutionalBias": "中性",
    "pbr": null,
    "_updated": "2026-07-10T12:12:09.817094",
    "_source": "twse"
  },
  "2317": {
    "price": 237.5,
    "change": 0.0,
    "changePct": 0.0,
    "weekChangePct": -0.63,
    "volume": 40528,
    "pe": null,
    "institutionalScore": 50,
    "institutionalBias": "中性",
    "pbr": null,
    "_updated": "2026-07-10T12:12:14.924221",
    "_source": "twse"
  },
  "2454": {
    "price": 3925.0,
    "change": -70.0,
    "changePct": -1.75,
    "weekChangePct": -9.67,
    "volume": 7371,
    "pe": null,
    "foreign": 162,
    "investment": 0,
    "dealer": -129,
    "foreignDays": 1,
    "investmentDays": -1,
    "dealerDays": -1,
    "institutionalScore": 52,
    "institutionalBias": "中性",
    "pbr": null,
    "_updated": "2026-07-10T12:12:20.523561",
    "_source": "twse"
  },
  "2881": {
    "price": 124.5,
    "change": -1.5,
    "changePct": -1.19,
    "weekChangePct": 4.18,
    "volume": 25389,
    "pe": null,
    "institutionalScore": 50,
    "institutionalBias": "中性",
    "pbr": null,
    "_updated": "2026-07-10T12:12:25.219006",
    "_source": "twse"
  },
  "2382": {
    "price": 373.5,
    "change": -3.5,
    "changePct": -0.93,
    "weekChangePct": 1.22,
    "volume": 13994,
    "pe": null,
    "institutionalScore": 50,
    "institutionalBias": "中性",
    "pbr": null,
    "_updated": "2026-07-10T12:12:30.110829",
    "_source": "twse"
  }
}